pycaracoltv/__init__.py
pycaracoltv/caracoltv.py
pycaracoltv/caracoltv_utils.py
pycaracoltv-0.5.0.dist-info/LICENSE
pycaracoltv-0.5.0.dist-info/METADATA
pycaracoltv-0.5.0.dist-info/WHEEL
pycaracoltv-0.5.0.dist-info/top_level.txt
pycaracoltv-0.5.0.dist-info/RECORD
