Metadata-Version: 2.1
Name: pycaracoltv
Version: 0.5.0
Summary: pycaracoltv es una herramienta de web scraping para extraer videos, imágenes y otros tipos de metadatos de la página caracoltv.com
Home-page: https://github.com/CalumRakk/pycaracoltv
Author: Leo
Author-email: leocasti2@gmail.com
License: UNKNOWN
Platform: UNKNOWN
License-File: LICENSE
Requires-Dist: lxml
Requires-Dist: requests
